pipdisttest/__init__.py
pipdisttest/test.py
pipdisttest2-0.0.2.dist-info/METADATA
pipdisttest2-0.0.2.dist-info/WHEEL
pipdisttest2-0.0.2.dist-info/top_level.txt
pipdisttest2-0.0.2.dist-info/RECORD
